dnsdefender/__init__.py
dnsdefender/cli.py
dnsdefender/scan.py
dnsdefender/version.py
dnsdefender/aws/__init__.py
dnsdefender/aws/ec2.py
dnsdefender/aws/eips.py
dnsdefender/aws/globalaccelerator.py
dnsdefender/aws/lb.py
dnsdefender/aws/route53.py
dnsdefender/cloudFlare/__init__.py
dnsdefender/cloudFlare/records.py
dnsdefender/utils/constants.py
dnsdefender/utils/filters.py
dnsdefender/utils/old_dns_entries.py
dnsdefender/utils/result.py
dnsdefender/utils/takeover.py
dnsdefender/utils/whitelist.py
uc_engg_dnsdefender-1.0.7.dist-info/LICENSE
uc_engg_dnsdefender-1.0.7.dist-info/METADATA
uc_engg_dnsdefender-1.0.7.dist-info/WHEEL
uc_engg_dnsdefender-1.0.7.dist-info/entry_points.txt
uc_engg_dnsdefender-1.0.7.dist-info/top_level.txt
uc_engg_dnsdefender-1.0.7.dist-info/RECORD
