Metadata-Version: 2.2
Name: uc-engg-dnsdefender
Version: 1.0.7
Summary: Tool to analyze and eliminate dangling elastic IPs in AWS accounts
Author-email: UC Engineering <abhinavgautam@urbancompany.com>
Project-URL: Homepage, https://gitlab.urbanclap.com/urbanclap/dangling-dns-service
Project-URL: Bug Tracker, https://gitlab.urbanclap.com/urbanclap/dangling-dns-service/-/issues
Requires-Python: >=3.6
License-File: LICENSE
Requires-Dist: click
Requires-Dist: boto3
Requires-Dist: awsipranges
Requires-Dist: requests
Requires-Dist: cloudflare
Requires-Dist: slack-sdk
Requires-Dist: pydantic==2.9.2
Requires-Dist: httpx==0.27.2
